FlaskStarter/__init__.py
FlaskStarter/src/FlaskStarter.py
FlaskStarter/src/__init__.py
FlaskStarter/test/__init__.py
FlaskStarter/test/deleter.py
FlaskStarter/test/test_FlaskStarter.py
FlaskStarterApp-1.0.2.dist-info/LICENSE.txt
FlaskStarterApp-1.0.2.dist-info/METADATA
FlaskStarterApp-1.0.2.dist-info/WHEEL
FlaskStarterApp-1.0.2.dist-info/top_level.txt
FlaskStarterApp-1.0.2.dist-info/RECORD
